lite/__init__.py
lite/cnn.py
lite/functional.py
lite/losses.py
lite/nn.py
lite/optim.py
lite/qnet.py
lite/rnn.py
lite/scipy_optim.py
lite/tensor.py
lite/utils.py
lite/vision.py
PyLitedl-0.0.9.dist-info/METADATA
PyLitedl-0.0.9.dist-info/WHEEL
PyLitedl-0.0.9.dist-info/top_level.txt
PyLitedl-0.0.9.dist-info/RECORD
